Workbook

Sheet Outflow
A1: iCloud Canvas of Dreams - Phasing and Cash Outflow Plan
A2: # | B2: Outflow Stream | C2: Land area allocation | D2: Land area allocation | E2: BUA | F2: Rate | G2: Budgeted Construction Cost | H2: Construction Duration | I2: Start Date | J2: Qtr 3 | K2: Qtr 4 | L2: Qtr 1 | M2: Qtr 2 | N2: Qtr 3 | O2: Qtr 4 | P2: Qtr 1 | Q2: Qtr 2 | R2: Qtr 3 | S2: Qtr 4 | T2: Qtr 1 | U2: Qtr 2 | V2: Qtr 3 | W2: Qtr 4 | X2: Qtr 1 | Y2: Qtr 2 | Z2: Qtr 3 | AA2: Qtr 4 | AB2: Qtr 1 | AC2: Qtr 2 | AD2: Qtr 3 | AE2: Qtr 4 | AF2: Qtr 1 | AG2: Qtr 2 | AH2: Qtr 3 | AI2: Qtr 4
C3: Acres | D3: Sft | E3: Sft | F3: Rs. | G3: Cr | H3: months | J3: FY 2026-27 | L3: FY 2027-28 | P3: FY 2028-29 | T3: FY 2029-30 | X3: FY 2030-31 | AB3: FY 2031-32 | AF3: FY 2032-33
A4: 1 | B4: Land Acquisition (80 acres @ Rs 5 Lakh/acre) | C4: 100 | D4: =100*4047*10.764 -> 4356190.8 | F4: 1147 | G4: =D4*F4/10000000 -> 499.65508 | H4: 18 | I4: 46296 | J4: 50 | K4: 80 | L4: 80 | M4: 80 | N4: 80 | O4: 80 | P4: 50 | AJ4: =SUM(J4:AI4) -> 500
A5: 2 | B5: Infrastructure Development (@ Rs. 75 Lakh/acre) | C5: 100 | D5: =100*4047*10.764 -> 4356190.8 | F5: 172 | G5: =D5*F5/10000000 -> 74.926482 | H5: 36 | I5: 46296 | J5: 1 | K5: 2 | L5: 6.25 | M5: 6.25 | N5: 6.25 | O5: 7.5 | P5: 7.5 | Q5: 7.5 | R5: 7.5 | S5: 8 | T5: 6 | U5: 6 | V5: 3 | AJ5: =SUM(J5:AI5) -> 74.75
A6: Land Acquisition & Dev. Cost/ Sft | C6: 100 | D6: =D5 -> 4356190.8 | F6: =SUM(F4:F5) -> 1319 | G6: =SUM(G4:G5) -> 574.58157 | AJ6: =SUM(J6:AI6) -> 0
A7: 3 | B7: Sales-cum-Site Office plus Arch, Road and Bellmouth at entrance (budgeted Rs. 5 cr) | E7: 12000 | F7: 4000 | G7: =E7*F7/10000000 -> 4.8 | H7: 6 | I7: 46296 | J7: 2 | K7: 2 | L7: 1 | AJ7: =SUM(J7:AI7) -> 5
A8: 4 | B8: Package 1 - 100-unit Apartment Block | C8: 1.2 | D8: =C8*4047*10.764 -> 52274.29 | E8: =1500*100 -> 150000 | F8: 3000 | G8: =E8*F8/10000000 -> 45 | H8: 24 | I8: 46388 | K8: 1 | L8: 3 | M8: 3 | N8: 5 | O8: 5 | P8: 6 | Q8: 7 | R8: 7 | S8: 8 | AJ8: =SUM(J8:AI8) -> 45
A9: 5 | B9: Package 1 - 60-unit Villas | C9: 3 | D9: =C9*4047*10.764 -> 130685.72 | E9: =60*1750 -> 105000 | F9: 3000 | G9: =E9*F9/10000000 -> 31.5 | H9: 36 | I9: 46388 | K9: 1 | L9: 3 | M9: 3 | N9: 3 | O9: 3 | P9: 3 | Q9: 3 | R9: 2 | S9: 2 | T9: 3 | U9: 3 | V9: 3 | AJ9: =SUM(J9:AI9) -> 32
A10: 6 | B10: Package 1 - 32-unit Senior Living | C10: 1 | D10: =C10*4047*10.764 -> 43561.908 | E10: =32*1000 -> 32000 | F10: 4000 | G10: =F10*E10/10000000 -> 12.8 | H10: 36 | I10: 46388 | K10: 1 | L10: 1 | M10: 1 | N10: 1 | O10: 1 | P10: 1 | Q10: 1 | R10: 1 | S10: 1 | T10: 1 | U10: 1 | V10: 1 | W10: 1 | AJ10: =SUM(J10:AI10) -> 13
A11: 7 | B11: School | C11: 6 | D11: =C11*4047*10.764 -> 261371.45 | E11: 200000 | F11: 3000 | G11: =E11*F11/10000000 -> 60 | H11: 18 | I11: 46661 | N11: 9 | O11: 9 | P11: 9 | Q11: 9 | R11: 12 | S11: 12 | AJ11: =SUM(J11:AI11) -> 60
A12: 8 | B12: Hospital | C12: 5 | D12: =C12*4047*10.764 -> 217809.54 | E12: 300000 | F12: 5000 | G12: =E12*F12/10000000 -> 150 | H12: 30 | I12: 46661 | N12: 12 | O12: 12 | P12: 15 | Q12: 15 | R12: 15 | S12: 15 | T12: 15 | U12: 15 | V12: 18 | W12: 18 | AJ12: =SUM(J12:AI12) -> 150
A13: 9 | B13: Senior Citizens Enclave (Balance) - 160 units | C13: 5 | D13: =C13*4047*10.764 -> 217809.54 | E13: =160*1000 -> 160000 | F13: 4000 | G13: =E13*F13/10000000 -> 64 | H13: 24 | I13: 46753 | O13: 7 | P13: 7 | Q13: 7 | R13: 8 | S13: 8 | T13: 9 | U13: 9 | V13: 9 | AJ13: =SUM(J13:AI13) -> 64
A14: 10 | B14: Clubhouse Annex | C14: 1 | D14: =C14*4047*10.764 -> 43561.908 | E14: 10000 | F14: 4000 | G14: =E14*F14/10000000 -> 4 | H14: 12 | I14: 46844 | P14: 1 | Q14: 1 | R14: 1 | S14: 1 | AJ14: =SUM(J14:AI14) -> 4
A15: 11 | B15: Clubhouse with mini-golf | C15: 7 | D15: =C15*4047*10.764 -> 304933.36 | E15: 40000 | F15: 6000 | G15: =E15*F15/10000000 -> 24 | H15: 24 | I15: 47209 | T15: 3 | U15: 3 | V15: 3 | W15: 3 | X15: 3 | Y15: 3 | Z15: 3 | AA15: 3 | AJ15: =SUM(J15:AI15) -> 24
A16: 12 | B16: Commercial Complex | C16: 4 | D16: =C16*4047*10.764 -> 174247.63 | E16: 300000 | F16: 4500 | G16: =E16*F16/10000000 -> 135 | H16: 30 | I16: 47209 | T16: 11 | U16: 12 | V16: 12 | W16: 12 | X16: 14 | Y16: 14 | Z16: 15 | AA16: 15 | AB16: 15 | AC16: 15 | AJ16: =SUM(J16:AI16) -> 135
A17: 13 | B17: Balance Development - 640-unit Villas | C17: =640/20 -> 32 | D17: =C17*4047*10.764 -> 1393981.1 | E17: =640*2000 -> 1280000 | F17: 3000 | G17: =E17*F17/10000000 -> 384 | H17: 48 | I17: 47119 | S17: 20 | T17: 20 | U17: 24 | V17: 25 | W17: 25 | X17: 25 | Y17: 25 | Z17: 25 | AA17: 25 | AB17: 25 | AC17: 25 | AD17: 25 | AE17: 25 | AF17: 25 | AG17: 25 | AH17: 20 | AJ17: =SUM(J17:AI17) -> 384
A18: 14 | B18: Balance Development - 900-unit Apartments | C18: 10.8 | D18: =C18*4047*10.764 -> 470468.61 | E18: =900*1500 -> 1350000 | F18: 3000 | G18: =E18*F18/10000000 -> 405 | H18: 48 | I18: 47119 | S18: 24 | T18: 24 | U18: 24 | V18: 24 | W18: 24 | X18: 24 | Y18: 24 | Z18: 25 | AA18: 25 | AB18: 25 | AC18: 25 | AD18: 25 | AE18: 25 | AF18: 27 | AG18: 30 | AH18: 30 | AJ18: =SUM(J18:AI18) -> 405 | AK18: =SUM(AJ4:AJ18) -> 1895.75
A19: BUA & Avg. Cost of Const./ Sft | C19: =SUM(C8:C18) -> 76 | D19: =SUM(D8:D18) -> 3310705 | E19: =SUM(E7:E18) -> 3939000 | F19: =G19*10000000/E19 -> 3351.3582 | G19: =SUM(G7:G18) -> 1320.1 | H19: 75 months | I19: Oct 2026 to Dec 2032 | J19: =SUM(J7:J18)+SUM(J4:J5) -> 53 | K19: =SUM(K7:K18)+SUM(K4:K5) -> 87 | L19: =SUM(L7:L18)+SUM(L4:L5) -> 94.25 | M19: =SUM(M7:M18)+SUM(M4:M5) -> 93.25 | N19: =SUM(N7:N18)+SUM(N4:N5) -> 116.25 | O19: =SUM(O7:O18)+SUM(O4:O5) -> 124.5 | P19: =SUM(P7:P18)+SUM(P4:P5) -> 99.5 | Q19: =SUM(Q7:Q18)+SUM(Q4:Q5) -> 50.5 | ... AI19: =SUM(AI7:AI18)+SUM(AI4:AI5) -> 0 | AK19: =SUM(J19:AJ19) -> 1895.75
A20: TOTAL PROJECT COST | G20: =G19+G6 -> 1894.6816 | J20: =SUM(J19:K19) -> 140 | L20: =SUM(L19:O19) -> 428.25 | P20: =SUM(P19:S19) -> 302.5 | T20: =SUM(T19:W19) -> 370 | X20: =SUM(X19:AA19) -> 268 | AB20: =SUM(AB19:AE19) -> 230 | AF20: =SUM(AF19:AI19) -> 157 | AK20: =SUM(J4:AI18) -> 1895.75
B22: Total Land Cost | E22: =G6 -> 574.58157 | F22: Cr
B23: Total BUA | E23: =E19 -> 3939000 | F23: sft
B24: Land Cost/BUA | E24: =E22*10000000/E23 -> 1458.6991 | F24: Rs./sft
B25: Margin on Land | E25: =1+F25 -> 1.25 | F25: 0.25
B26: Margin on BUA | E26: 1.2 | F26: 0.2
B27: Interest on Debt | E27: 1.15 | F27: 0.15

Sheet Inflow
A1: iCloud Canvas of Dreams - Phasing and Cash Inflow Plan
A2: # | B2: Outflow Stream | C2: Budgeted Cost Price | D2: Target Sale Price | E2: Qtr 3 | F2: Qtr 4 | G2: Qtr 1 | H2: Qtr 2 | I2: Qtr 3 | J2: Qtr 4 | K2: Qtr 1 | L2: Qtr 2 | M2: Qtr 3 | N2: Qtr 4 | O2: Qtr 1 | P2: Qtr 2 | Q2: Qtr 3 | R2: Qtr 4 | S2: Qtr 1 | T2: Qtr 2 | U2: Qtr 3 | V2: Qtr 4 | W2: Qtr 1 | X2: Qtr 2 | Y2: Qtr 3 | Z2: Qtr 4 | AA2: Qtr 1 | AB2: Qtr 2 | AC2: Qtr 3 | AD2: Qtr 4
C3: Cr | D3: Cr | E3: FY 2026-27 | G3: FY 2027-28 | K3: FY 2028-29 | O3: FY 2029-30 | S3: FY 2030-31 | W3: FY 2031-32 | AA3: FY 2032-33
A4: 1 | B4: Promoter Equity Infusion/ Internal Accruals | D4: =SUM(E4:AD4) -> 200 | E4: 54 | F4: 20 | G4: 20 | H4: 20 | I4: 20 | J4: 20 | K4: 16 | L4: 10 | M4: 10 | N4: 10 | AE4: =SUM(E4:AD4) -> 200
A5: 2 | B5: External Debt Drawdown | D5: =SUM(E5:AD5) -> 300 | F5: 100 | G5: 100 | H5: 100 | AE5: =SUM(E5:AD5) -> 300
D6: =SUM(D4:D5) -> 500
A7: 3 | B7: Land Acquisition & Dev Cost | C7: =Outflow!G6 -> 574.58157 | D7: 0 | AE7: =SUM(E7:AD7) -> 0
A8: 4 | B8: Sales-cum-Site Office plus Arch, Road and Bellmouth at entrance (budgeted Rs. 5 cr) | C8: =Outflow!G7 -> 4.8 | D8: 0 | AE8: =SUM(E8:AD8) -> 0
A9: 5 | B9: Package 1 - 100-unit Apartment Block | C9: =Outflow!G8 -> 45 | D9: =(Outflow!G8*Outflow!E$27^(Outflow!H8/12)-Outflow!G8)+(Outflow!D8*Outflow!E$24/10000000*Outflow!E$25)+(Outflow!G8*Outflow!E$26) -> 78.044057 | F9: =0.2*D9 -> 15.608811 | G9: =F9 -> 15.608811 | H9: 6 | I9: 6 | J9: 6 | K9: 6 | L9: 6 | M9: 6 | N9: 6 | O9: 5 | AE9: =SUM(E9:AD9) -> 78.217623
A10: 6 | B10: Package 1 - 60-unit Villas | C10: =Outflow!G9 -> 31.5 | D10: =(Outflow!G9*Outflow!E$27^(Outflow!H9/12)-Outflow!G9)+(Outflow!D9*Outflow!E$24/10000000*Outflow!E$25)+(Outflow!G9*Outflow!E$26) -> 78.036456 | F10: =0.2*D10 -> 15.607291 | G10: =F10 -> 15.607291 | H10: 4 | I10: 4 | J10: 4 | K10: 5 | L10: 5 | M10: 5 | N10: 5 | O10: 5 | P10: 5 | Q10: 5 | AE10: =SUM(E10:AD10) -> 78.214582
A11: 7 | B11: Package 1 - 32-unit Senior Living | C11: =Outflow!G10 -> 12.8 | D11: =(Outflow!G10*Outflow!E$27^(Outflow!H10/12)-Outflow!G10)+(Outflow!D10*Outflow!E$24/10000000*Outflow!E$25)+(Outflow!G10*Outflow!E$26) -> 29.970164 | F11: =0.2*D11 -> 5.9940329 | G11: =F11 -> 5.9940329 | H11: 1 | I11: 1 | J11: 1 | K11: 1 | L11: 2 | M11: 2 | N11: 2 | O11: 2 | P11: 2 | Q11: 2 | R11: 2 | AE11: =SUM(E11:AD11) -> 29.988066
A12: 8 | B12: School | C12: =Outflow!G11 -> 60 | D12: =(Outflow!G11*Outflow!E$27^(Outflow!H11/12)-Outflow!G11)+(Outflow!D11*Outflow!E$24/10000000*Outflow!E$25)+(Outflow!G11*Outflow!E$26) -> 133.65204 | I12: 18 | J12: 18 | K12: 18 | L12: 20 | M12: 30 | N12: 30 | AE12: =SUM(E12:AD12) -> 134
A13: 9 | B13: Hospital | C13: =Outflow!G12 -> 150 | D13: =(Outflow!G12*Outflow!E$27^(Outflow!H12/12)-Outflow!G12)+(Outflow!D12*Outflow!E$24/10000000*Outflow!E$25)+(Outflow!G12*Outflow!E$26) -> 282.44831 | I13: 20 | J13: 20 | K13: 28 | L13: 28 | M13: 28 | N13: 28 | O13: 30 | P13: 30 | Q13: 30 | R13: 40 | AE13: =SUM(E13:AD13) -> 282
A14: 10 | B14: Senior Citizens Enclave (Balance) - 160 units | C14: =Outflow!G13 -> 64 | D14: =(Outflow!G13*Outflow!E$27^(Outflow!H13/12)-Outflow!G13)+(Outflow!D13*Outflow!E$24/10000000*Outflow!E$25)+(Outflow!G13*Outflow!E$26) -> 137.15482 | J14: 25 | K14: 12 | L14: 12 | M14: 12 | N14: 20 | O14: 20 | P14: 20 | Q14: 16 | AE14: =SUM(E14:AD14) -> 137
A15: 11 | B15: Clubhouse Annex | C15: =Outflow!G14 -> 4 | D15: =(Outflow!G14*Outflow!E$27^(Outflow!H14/12)-Outflow!G14)+(Outflow!D14*Outflow!E$24/10000000*Outflow!E$25)+(Outflow!G14*Outflow!E$26) -> 13.342964 | K15: 1 | L15: 1 | M15: 1 | N15: 1 | O15: 1 | P15: 1 | Q15: 1 | R15: 1 | S15: 1 | T15: 1 | U15: 1 | V15: 1 | W15: 1 | AE15: =SUM(E15:AD15) -> 13
A16: 12 | B16: Clubhouse with mini-golf | C16: =Outflow!G15 -> 24 | D16: =(Outflow!G15*Outflow!E$27^(Outflow!H15/12)-Outflow!G15)+(Outflow!D15*Outflow!E$24/10000000*Outflow!E$25)+(Outflow!G15*Outflow!E$26) -> 92.140751 | O16: 6 | P16: 6 | Q16: 6 | R16: 6 | S16: 6 | T16: 6 | U16: 6 | V16: 6 | W16: 6 | X16: 6 | Y16: 6 | Z16: 6 | AA16: 6 | AB16: 6 | AC16: 8 | AE16: =SUM(E16:AD16) -> 92
A17: 13 | B17: Commercial Complex | C17: =Outflow!G16 -> 135 | D17: =(Outflow!G16*Outflow!E$27^(Outflow!H16/12)-Outflow!G16)+(Outflow!D16*Outflow!E$24/10000000*Outflow!E$25)+(Outflow!G16*Outflow!E$26) -> 250.232 | O17: 20 | P17: 20 | Q17: 20 | R17: 25 | S17: 25 | T17: 25 | U17: 25 | V17: 25 | W17: 25 | X17: 25 | Y17: 15 | AE17: =SUM(E17:AD17) -> 250
A18: 14 | B18: Balance Development - 640-unit Villas | C18: =Outflow!G17 -> 384 | D18: =(Outflow!G17*Outflow!E$27^(Outflow!H17/12)-Outflow!G17)+(Outflow!D17*Outflow!E$24/10000000*Outflow!E$25)+(Outflow!G17*Outflow!E$26) -> 1002.5933 | N18: 50 | O18: 50 | P18: 50 | Q18: 50 | R18: 50 | S18: 50 | T18: 60 | U18: 60 | V18: 60 | W18: 60 | X18: 60 | Y18: 70 | Z18: 70 | AA18: 70 | AB18: 70 | AC18: 70 | AD18: 53 | AE18: =SUM(E18:AD18) -> 1003
A19: 15 | B19: Balance Development - 900-unit Apartments | C19: =Outflow!G18 -> 405 | D19: =(Outflow!G18*Outflow!E$27^(Outflow!H18/12)-Outflow!G18)+(Outflow!D18*Outflow!E$24/10000000*Outflow!E$25)+(Outflow!G18*Outflow!E$26) -> 875.13155 | N19: 45 | O19: 45 | P19: 45 | Q19: 48 | R19: 48 | S19: 48 | T19: 48 | U19: 48 | V19: 50 | W19: 50 | X19: 50 | Y19: 50 | Z19: 60 | AA19: 60 | AB19: 60 | AC19: 60 | AD19: 60 | AE19: =SUM(E19:AD19) -> 875
A20: TOTAL BUDGET & TARGET SALE PRICE | C20: =SUM(C7:C19) -> 1894.6816 | D20: =SUM(D8:D19) -> 2972.7464 | E20: =SUM(E4:E19) -> 54 | F20: =SUM(F4:F19) -> 157.21014 | G20: =SUM(G4:G19) -> 157.21014 | H20: =SUM(H4:H19) -> 131 | I20: =SUM(I4:I19) -> 69 | J20: =SUM(J4:J19) -> 94 | K20: =SUM(K4:K19) -> 87 | L20: =SUM(L4:L19) -> 84 | ... AD20: =SUM(AD4:AD19) -> 113 | AE20: =SUM(E20:AD20) -> 3472.4203 | AF20: =SUM(AE4:AE19) -> 3472.4203
E21: =SUM(E20:F20) -> 211.21014 | G21: =SUM(G20:J20) -> 451.21014 | K21: =SUM(K20:N20) -> 462 | O21: =SUM(O20:R20) -> 713 | S21: =SUM(S20:V20) -> 552 | W21: =SUM(W20:Z20) -> 560 | AA21: =SUM(AA20:AD20) -> 523 | AF21: =D6+D20 -> 3472.7464
AF22: =SUM(E4:AD19) -> 3472.4203
A23: Net Surplus/ (deficit) before Interest/EMI (Period-wise) | E23: =E20-Outflow!J19 -> 1 | F23: =F20-Outflow!K19 -> 70.210135 | G23: =G20-Outflow!L19 -> 62.960135 | H23: =H20-Outflow!M19 -> 37.75 | I23: =I20-Outflow!N19 -> -47.25 | J23: =J20-Outflow!O19 -> -30.5 | K23: =K20-Outflow!P19 -> -12.5 | L23: =L20-Outflow!Q19 -> 33.5 | ... AD23: =AD20-Outflow!AI19 -> 113 | AE23: =SUM(E23:AD23) -> 1576.6703
E24: =E23+F23 -> 71.210135 | G24: =SUM(G23:J23) -> 22.960135 | K24: =SUM(K23:N23) -> 159.5 | O24: =SUM(O23:R23) -> 343 | S24: =SUM(S23:V23) -> 284 | W24: =SUM(W23:Z23) -> 330 | AA24: =SUM(AA23:AD23) -> 366
A26: Debt Interest and EMI repayments @ 15% Interest | E26: 0 | F26: 3.75 | G26: 7.5 | H26: 11.25 | I26: 11.25 | J26: 11.25 | K26: 11.25 | L26: 11.25 | M26: 11.25 | N26: 24.08 | O26: 24 | P26: 24 | Q26: 24 | R26: 24 | S26: 24 | T26: 24 | U26: 24 | V26: 24 | W26: 24 | X26: 24 | Y26: 24 | Z26: 24 | AA26: 24 | AB26: 24 | AC26: 24 | AD26: 25 | AE26: =SUM(E26:AD26) -> 487.83
E27: =E26+F26 -> 3.75 | G27: =SUM(G26:J26) -> 41.25 | K27: =SUM(K26:N26) -> 57.83 | O27: =SUM(O26:R26) -> 96 | S27: =SUM(S26:V26) -> 96 | W27: =SUM(W26:Z26) -> 96 | AA27: =SUM(AA26:AD26) -> 97
A29: Net Surplus/ (deficit) after Interest/EMI (Period -wise) | E29: =E23-E26 -> 1 | F29: =F23-F26 -> 66.460135 | G29: =G23-G26 -> 55.460135 | H29: =H23-H26 -> 26.5 | I29: =I23-I26 -> -58.5 | J29: =J23-J26 -> -41.75 | K29: =K23-K26 -> -23.75 | L29: =L23-L26 -> 22.25 | ... AD29: =AD23-AD26 -> 88 | AE29: =SUM(E29:AD29) -> 1088.8403
E30: =E29+F29 -> 67.460135 | G30: =SUM(G29:J29) -> -18.289865 | K30: =SUM(K29:N29) -> 101.67 | O30: =SUM(O29:R29) -> 247 | S30: =SUM(S29:V29) -> 188 | W30: =SUM(W29:Z29) -> 234 | AA30: =SUM(AA29:AD29) -> 269
A32: Net Surplus/ (deficit) after Interest/EMI (CUMULATIVE) | E32: =E29 -> 1 | F32: =E29+F29 -> 67.460135 | G32: =F32+G29 -> 122.92027 | H32: =G32+H29 -> 149.42027 | I32: =H32+I29 -> 90.920271 | J32: =I32+J29 -> 49.170271 | K32: =J32+K29 -> 25.420271 | L32: =K32+L29 -> 47.670271 | M32: =L32+M29 -> 76.920271 | N32: =M32+N29 -> 150.84027 | ... AD32: =AC32+AD29 -> 1088.8403
E33: =F32 -> 67.460135 | G33: =J32 -> 49.170271 | K33: =N32 -> 150.84027 | O33: =R32 -> 397.84027 | S33: =V32 -> 585.84027 | W33: =Z32 -> 819.84027 | AA33: =AD32 -> 1088.8403
